pylogit/__init__.py
pylogit/asym_logit.py
pylogit/base_multinomial_cm_v2.py
pylogit/bootstrap.py
pylogit/bootstrap_abc.py
pylogit/bootstrap_calcs.py
pylogit/bootstrap_mle.py
pylogit/bootstrap_sampler.py
pylogit/bootstrap_utils.py
pylogit/choice_calcs.py
pylogit/choice_tools.py
pylogit/clog_log.py
pylogit/conditional_logit.py
pylogit/construct_estimator.py
pylogit/display_names.py
pylogit/estimation.py
pylogit/mixed_logit.py
pylogit/mixed_logit_calcs.py
pylogit/nested_choice_calcs.py
pylogit/nested_logit.py
pylogit/pylogit.py
pylogit/scobit.py
pylogit/uneven_logit.py
pylogit-1.0.1.dist-info/LICENSE.txt
pylogit-1.0.1.dist-info/WHEEL
pylogit-1.0.1.dist-info/METADATA
pylogit-1.0.1.dist-info/RECORD
