Metadata-Version: 1.1
Name: pylogit
Version: 1.0.1
Summary: Created on Mon Mar 14 15:33:07 2016
Home-page: https://github.com/timothyb0912/pylogit
Author: Timothy Brathwaite
Author-email: timothyb0912@gmail.com
